Metadata-Version: 1.0
Name: bccdl
Version: 0.1.0
Summary: bilibili CC subtitle downloader
Home-page: https://github.com/guomo233/bccdl
Author: guomo233
Author-email: gmlihanxi@gmail.com
License: UNKNOWN
Platform: UNKNOWN
